dubscript/__init__.py
dubscript/core.py
dubscript-0.1.dist-info/LICENSE
dubscript-0.1.dist-info/METADATA
dubscript-0.1.dist-info/WHEEL
dubscript-0.1.dist-info/top_level.txt
dubscript-0.1.dist-info/RECORD
