Metadata-Version: 2.1
Name: dubscript
Version: 0.1
Summary: Easily dub audio files using a simple command script.
Home-page: https://gitlab.com/giuliobottari/dub-script
Author: Giulio Bottari
Author-email: giuliobottari@gmail.com
License: MIT
Keywords: audio dub pydub
Platform: UNKNOWN
Classifier: Programming Language :: Python :: 3
Classifier: Intended Audience :: Developers
Requires-Dist: requests
Requires-Dist: pydub
